hepfile/__init__.py
hepfile/_version.py
hepfile/awkward_tools.py
hepfile/constants.py
hepfile/csv_tools.py
hepfile/df_tools.py
hepfile/dict_tools.py
hepfile/errors.py
hepfile/read.py
hepfile/write.py
hepfile-0.1.7.dist-info/LICENSE
hepfile-0.1.7.dist-info/METADATA
hepfile-0.1.7.dist-info/WHEEL
hepfile-0.1.7.dist-info/top_level.txt
hepfile-0.1.7.dist-info/RECORD
