Metadata-Version: 2.1
Name: hepfile
Version: 0.1.7
Author-email: Matt Bellis <mbellis@siena.edu>
License: 
Project-URL: Documentation, https://hepfile.github.io
Project-URL: Home, https://github.com/mattbellis/hepfile
Classifier: License :: OSI Approved :: BSD License
Classifier: Topic :: Scientific/Engineering
Classifier: Intended Audience :: Science/Research
Classifier: Intended Audience :: Developers
Classifier: Operating System :: OS Independent
Classifier: License :: OSI Approved :: BSD License
Classifier: Programming Language :: Python
Classifier: Programming Language :: Python :: 3
Classifier: Programming Language :: Python :: 3.9
Classifier: Programming Language :: Python :: 3.10
Classifier: Programming Language :: Python :: 3.11
Classifier: Development Status :: 1 - Planning
Requires-Python: >=3.9
License-File: LICENSE
Requires-Dist: numpy (>=1.13.3)
Requires-Dist: h5py
Provides-Extra: all
Requires-Dist: hepfile[awkward,pandas] ; extra == 'all'
Provides-Extra: awkward
Requires-Dist: awkward (>2) ; extra == 'awkward'
Provides-Extra: dev
Requires-Dist: hepfile[all] ; extra == 'dev'
Requires-Dist: pre-commit ; extra == 'dev'
Requires-Dist: jupyter ; extra == 'dev'
Requires-Dist: mistune ; extra == 'dev'
Requires-Dist: pytest ; extra == 'dev'
Requires-Dist: ruff ; extra == 'dev'
Provides-Extra: docs
Requires-Dist: hepfile[all] ; extra == 'docs'
Requires-Dist: Sphinx (>=3.0.0) ; extra == 'docs'
Requires-Dist: myst-parser (>=0.13) ; extra == 'docs'
Requires-Dist: nbsphinx (>=0.9.1) ; extra == 'docs'
Requires-Dist: sphinx-book-theme (>=0.0.33) ; extra == 'docs'
Requires-Dist: sphinx-copybutton ; extra == 'docs'
Requires-Dist: autodoc ; extra == 'docs'
Requires-Dist: ipykernel ; extra == 'docs'
Provides-Extra: learn
Requires-Dist: hepfile[awkward,pandas] ; extra == 'learn'
Requires-Dist: astropy ; extra == 'learn'
Provides-Extra: pandas
Requires-Dist: pandas ; extra == 'pandas'
